phoopy/__init__.py
phoopy/console/__init__.py
phoopy/console/abstract_command.py
phoopy/console/application.py
phoopy/console/proxy_command.py
phoopy/console/helper/__init__.py
phoopy/console/helper/date_helper.py
phoopy/console/helper/output_helper.py
phoopy/console/helper/string_helper.py
phoopy_console-1.2.0.dist-info/LICENSE.md
phoopy_console-1.2.0.dist-info/METADATA
phoopy_console-1.2.0.dist-info/WHEEL
phoopy_console-1.2.0.dist-info/top_level.txt
phoopy_console-1.2.0.dist-info/RECORD
