Metadata-Version: 2.1
Name: phoopy-console
Version: 1.2.0
Summary: Console library for phoopy framework
Home-page: https://github.com/phoopy/phoopy-console
Author: Phoopy
Author-email: reisraff@gmail.com
License: MIT
Platform: UNKNOWN
Classifier: Operating System :: OS Independent
Classifier: Development Status :: 5 - Production/Stable
Classifier: Topic :: Software Development :: Libraries :: Python Modules
Classifier: License :: OSI Approved :: MIT License
Classifier: Programming Language :: Python :: 2.6
Classifier: Programming Language :: Python :: 2.7
Classifier: Programming Language :: Python :: 3
Classifier: Programming Language :: Python :: 3.2
Classifier: Programming Language :: Python :: 3.3
Classifier: Programming Language :: Python :: 3.4
Classifier: Programming Language :: Python :: 3.5
Requires-Dist: cleo (==0.6.8)
Requires-Dist: phoopy-kernel (<1.3.0,>=1.2.0)
